Workbook
Name cid: CustomersData[Cust_ID]
Name hsncode: Table46[HSN Code]

Sheet DashBoard 
M12: Notifications!!
M13: {=_xlfn._xlws.FILTER(Table8[Notification],Table8[Notification]<>"")} -> 📞 Printer Needs to re-order ! PH 9874561231
M14: 📞 Desktop Needs to re-order ! PH 9874561231
M15: 📞 Keyboard Needs to re-order ! PH 9874561231
M16: 📞 Camera Needs to re-order ! PH 9874561231
M17: 📞 Headphone Needs to re-order ! PH 9874561231
M18: 📞 Tablets Needs to re-order ! PH 9874561231

Sheet Customers
D7: Cust_ID | E7: Name | F7: Email | G7: Address
D8: 100 | E8: Harsh | F8: Harsh@gmail.com | G8: Delhi,India
D9: 101 | E9: Ram Sales | F9: Ram@gmail.com | G9: 12122,Palwal,HR
D10: 102 | E10: Atul Ltd. | F10: Atul@gmail.com | G10: Faridabad,UP
D11: 103 | E11: Raghav | F11: Raghav@gmail.com | G11: Agra,UP
D12: 104 | E12: Amit | F12: Amit@gmail.com | G12: Gurgaon,Sec-16
D13: 105 | E13: Jain tel | F13: Jaintel@gmail.com | G13: Janpath,New Delhi
D14: 106 | E14: Relaince | F14: Relaince@gmail.com | G14: Prayagraj,UP

Sheet Product
E7: HSN Code | F7: Product Name | G7: Cost | H7: Selling Price
E8: N1001 | F8: SmartWatch | G8: 980 | H8: 1176
E9: N1002 | F9: Laptop HP i5 | G9: 34500 | H9: 41400
E10: N1003 | F10: Printer | G10: 4600 | H10: 5520
E11: N1004 | F11: Desktop | G11: 21000 | H11: 25200
E12: N1005 | F12: Mouse | G12: 200 | H12: 240
E13: N1006 | F13: Keyboard | G13: 340 | H13: 408
E14: N1007 | F14: Camera | G14: 52000 | H14: 62400
E15: N1008 | F15: Headphone | G15: 799 | H15: 958
E16: N1009 | F16: Speaker | G16: 870 | H16: 804
E17: N1010 | F17: Tablets | G17: 23500 | H17: 28200

Sheet Vendors
E7: HSN Code | F7: Product Name | G7: Vendor Name | H7: Phone | I7: Address
E8: N1001 | F8: SmartWatch | G8: Tech01 | H8: 9874561231 | I8: Faridabad
E9: N1002 | F9: Laptop HP i5 | G9: Tech02 | H9: 9874561231 | I9: Faridabad
E10: N1003 | F10: Printer | G10: Tech03 | H10: 9874561231 | I10: Faridabad
E11: N1004 | F11: Desktop | G11: Tech04 | H11: 9874561231 | I11: New Delhi
E12: N1005 | F12: Mouse | G12: Tech05 | H12: 9874561231 | I12: New Delhi
E13: N1006 | F13: Keyboard | G13: Tech06 | H13: 9874561231 | I13: New Delhi
E14: N1007 | F14: Camera | G14: Tech07 | H14: 9874561231 | I14: Gurgon
E15: N1008 | F15: Headphone | G15: Tech08 | H15: 9874561231 | I15: Gurgon
E16: N1009 | F16: Speaker | G16: Tech09 | H16: 9874561231 | I16: Gurgon
E17: N1010 | F17: Tablets | G17: Tech10 | H17: 9874561231 | I17: Gurgon

Sheet New Entry
F8: Purchase Entry
F11: Sale entry

Sheet Purchase 
D7: HSN Code | E7: Product Name | F7: Vendor | G7: Date | H7: Units | I7: Cost | J7: Amount
D8: N1008 | E8: =IFERROR(VLOOKUP(PurchaseData[[#This Row],[HSN Code]],Table4[#All],2,0),"") -> Headphone | F8: =IFERROR(VLOOKUP(PurchaseData[[#This Row],[HSN Code]],Table46[#All],3,0),"") -> Tech08 | G8: 37987 | H8: 3 | I8: =IFERROR(VLOOKUP(PurchaseData[[#This Row],[HSN Code]],Table4[#All],3,0),"") -> 799 | J8: =IFERROR(PurchaseData[[#This Row],[Units]]*PurchaseData[[#This Row],[Cost]],"") -> 2397
D9: N1008 | E9: =IFERROR(VLOOKUP(PurchaseData[[#This Row],[HSN Code]],Table4[#All],2,0),"") -> Headphone | F9: =IFERROR(VLOOKUP(PurchaseData[[#This Row],[HSN Code]],Table46[#All],3,0),"") -> Tech08 | G9: 37987 | H9: 4 | I9: =IFERROR(VLOOKUP(PurchaseData[[#This Row],[HSN Code]],Table4[#All],3,0),"") -> 799 | J9: =IFERROR(PurchaseData[[#This Row],[Units]]*PurchaseData[[#This Row],[Cost]],"") -> 3196
D10: N1005 | E10: =IFERROR(VLOOKUP(PurchaseData[[#This Row],[HSN Code]],Table4[#All],2,0),"") -> Mouse | F10: =IFERROR(VLOOKUP(PurchaseData[[#This Row],[HSN Code]],Table46[#All],3,0),"") -> Tech05 | G10: 37987 | H10: 6 | I10: =IFERROR(VLOOKUP(PurchaseData[[#This Row],[HSN Code]],Table4[#All],3,0),"") -> 200 | J10: =IFERROR(PurchaseData[[#This Row],[Units]]*PurchaseData[[#This Row],[Cost]],"") -> 1200
D11: N1001 | E11: =IFERROR(VLOOKUP(PurchaseData[[#This Row],[HSN Code]],Table4[#All],2,0),"") -> SmartWatch | F11: =IFERROR(VLOOKUP(PurchaseData[[#This Row],[HSN Code]],Table46[#All],3,0),"") -> Tech01 | G11: 37987 | H11: 6 | I11: =IFERROR(VLOOKUP(PurchaseData[[#This Row],[HSN Code]],Table4[#All],3,0),"") -> 980 | J11: =IFERROR(PurchaseData[[#This Row],[Units]]*PurchaseData[[#This Row],[Cost]],"") -> 5880
D12: N1002 | E12: =IFERROR(VLOOKUP(PurchaseData[[#This Row],[HSN Code]],Table4[#All],2,0),"") -> Laptop HP i5 | F12: =IFERROR(VLOOKUP(PurchaseData[[#This Row],[HSN Code]],Table46[#All],3,0),"") -> Tech02 | G12: 37987 | H12: 3 | I12: =IFERROR(VLOOKUP(PurchaseData[[#This Row],[HSN Code]],Table4[#All],3,0),"") -> 34500 | J12: =IFERROR(PurchaseData[[#This Row],[Units]]*PurchaseData[[#This Row],[Cost]],"") -> 103500
D13: N1003 | E13: =IFERROR(VLOOKUP(PurchaseData[[#This Row],[HSN Code]],Table4[#All],2,0),"") -> Printer | F13: =IFERROR(VLOOKUP(PurchaseData[[#This Row],[HSN Code]],Table46[#All],3,0),"") -> Tech03 | G13: 37987 | H13: 3 | I13: =IFERROR(VLOOKUP(PurchaseData[[#This Row],[HSN Code]],Table4[#All],3,0),"") -> 4600 | J13: =IFERROR(PurchaseData[[#This Row],[Units]]*PurchaseData[[#This Row],[Cost]],"") -> 13800
D14: N1004 | E14: =IFERROR(VLOOKUP(PurchaseData[[#This Row],[HSN Code]],Table4[#All],2,0),"") -> Desktop | F14: =IFERROR(VLOOKUP(PurchaseData[[#This Row],[HSN Code]],Table46[#All],3,0),"") -> Tech04 | G14: 37987 | H14: 2 | I14: =IFERROR(VLOOKUP(PurchaseData[[#This Row],[HSN Code]],Table4[#All],3,0),"") -> 21000 | J14: =IFERROR(PurchaseData[[#This Row],[Units]]*PurchaseData[[#This Row],[Cost]],"") -> 42000
D15: N1009 | E15: =IFERROR(VLOOKUP(PurchaseData[[#This Row],[HSN Code]],Table4[#All],2,0),"") -> Speaker | F15: =IFERROR(VLOOKUP(PurchaseData[[#This Row],[HSN Code]],Table46[#All],3,0),"") -> Tech09 | G15: 37987 | H15: 2 | I15: =IFERROR(VLOOKUP(PurchaseData[[#This Row],[HSN Code]],Table4[#All],3,0),"") -> 870 | J15: =IFERROR(PurchaseData[[#This Row],[Units]]*PurchaseData[[#This Row],[Cost]],"") -> 1740
D16: N1004 | E16: =IFERROR(VLOOKUP(PurchaseData[[#This Row],[HSN Code]],Table4[#All],2,0),"") -> Desktop | F16: =IFERROR(VLOOKUP(PurchaseData[[#This Row],[HSN Code]],Table46[#All],3,0),"") -> Tech04 | G16: 37987 | H16: 6 | I16: =IFERROR(VLOOKUP(PurchaseData[[#This Row],[HSN Code]],Table4[#All],3,0),"") -> 21000 | J16: =IFERROR(PurchaseData[[#This Row],[Units]]*PurchaseData[[#This Row],[Cost]],"") -> 126000
D17: N1004 | E17: =IFERROR(VLOOKUP(PurchaseData[[#This Row],[HSN Code]],Table4[#All],2,0),"") -> Desktop | F17: =IFERROR(VLOOKUP(PurchaseData[[#This Row],[HSN Code]],Table46[#All],3,0),"") -> Tech04 | G17: 37987 | H17: 8 | I17: =IFERROR(VLOOKUP(PurchaseData[[#This Row],[HSN Code]],Table4[#All],3,0),"") -> 21000 | J17: =IFERROR(PurchaseData[[#This Row],[Units]]*PurchaseData[[#This Row],[Cost]],"") -> 168000

Sheet Sales
E8: Cust_ID | F8: Cust_Name | G8: HSN Code | H8: Product Name | I8: Date | J8: Stock(Units) | K8: Units | L8: Price | M8: Discount
E9: 103 | F9: =IFERROR(VLOOKUP(Table7[[#This Row],[Cust_ID]],CustomersData[#All],2,0),"") -> Raghav | G9: N1004 | H9: =IFERROR(VLOOKUP(Table7[[#This Row],[HSN Code]],Table4[#All],2,0),"") -> Desktop | I9: 46023 | J9: =IFERROR(VLOOKUP(Table7[[#This Row],[HSN Code]],Table8[#All],6,0),"") -> 12 | K9: 4 | L9: =IFERROR(VLOOKUP(Table7[[#This Row],[HSN Code]],Table4[#All],4,0),"") -> 25200 | M9: =IFERROR(Table7[[#This Row],[Units]]*Table7[[#This Row],[Price]],"") -> 100800
E10: 104 | F10: =IFERROR(VLOOKUP(Table7[[#This Row],[Cust_ID]],CustomersData[#All],2,0),"") -> Amit | G10: N1005 | H10: =IFERROR(VLOOKUP(Table7[[#This Row],[HSN Code]],Table4[#All],2,0),"") -> Mouse | I10: 46023 | J10: =IFERROR(VLOOKUP(Table7[[#This Row],[HSN Code]],Table8[#All],6,0),"") -> 0 | K10: 6 | L10: =IFERROR(VLOOKUP(Table7[[#This Row],[HSN Code]],Table4[#All],4,0),"") -> 240 | M10: =IFERROR(Table7[[#This Row],[Units]]*Table7[[#This Row],[Price]],"") -> 1440
E11: 104 | F11: =IFERROR(VLOOKUP(Table7[[#This Row],[Cust_ID]],CustomersData[#All],2,0),"") -> Amit | G11: N1006 | H11: =IFERROR(VLOOKUP(Table7[[#This Row],[HSN Code]],Table4[#All],2,0),"") -> Keyboard | I11: 46023 | J11: =IFERROR(VLOOKUP(Table7[[#This Row],[HSN Code]],Table8[#All],6,0),"") -> -2 | K11: 2 | L11: =IFERROR(VLOOKUP(Table7[[#This Row],[HSN Code]],Table4[#All],4,0),"") -> 408 | M11: =IFERROR(Table7[[#This Row],[Units]]*Table7[[#This Row],[Price]],"") -> 816
E12: 106 | F12: =IFERROR(VLOOKUP(Table7[[#This Row],[Cust_ID]],CustomersData[#All],2,0),"") -> Relaince | G12: N1007 | H12: =IFERROR(VLOOKUP(Table7[[#This Row],[HSN Code]],Table4[#All],2,0),"") -> Camera | I12: 46023 | J12: =IFERROR(VLOOKUP(Table7[[#This Row],[HSN Code]],Table8[#All],6,0),"") -> -5 | K12: 5 | L12: =IFERROR(VLOOKUP(Table7[[#This Row],[HSN Code]],Table4[#All],4,0),"") -> 62400 | M12: =IFERROR(Table7[[#This Row],[Units]]*Table7[[#This Row],[Price]],"") -> 312000
E13: 100 | F13: =IFERROR(VLOOKUP(Table7[[#This Row],[Cust_ID]],CustomersData[#All],2,0),"") -> Harsh | G13: N1008 | H13: =IFERROR(VLOOKUP(Table7[[#This Row],[HSN Code]],Table4[#All],2,0),"") -> Headphone | I13: 46023 | J13: =IFERROR(VLOOKUP(Table7[[#This Row],[HSN Code]],Table8[#All],6,0),"") -> 5 | K13: 2 | L13: =IFERROR(VLOOKUP(Table7[[#This Row],[HSN Code]],Table4[#All],4,0),"") -> 958 | M13: =IFERROR(Table7[[#This Row],[Units]]*Table7[[#This Row],[Price]],"") -> 1916
E14: 101 | F14: =IFERROR(VLOOKUP(Table7[[#This Row],[Cust_ID]],CustomersData[#All],2,0),"") -> Ram Sales | G14: N1009 | H14: =IFERROR(VLOOKUP(Table7[[#This Row],[HSN Code]],Table4[#All],2,0),"") -> Speaker | I14: 46023 | J14: =IFERROR(VLOOKUP(Table7[[#This Row],[HSN Code]],Table8[#All],6,0),"") -> -7 | K14: 6 | L14: =IFERROR(VLOOKUP(Table7[[#This Row],[HSN Code]],Table4[#All],4,0),"") -> 804 | M14: =IFERROR(Table7[[#This Row],[Units]]*Table7[[#This Row],[Price]],"") -> 4824
E15: 103 | F15: =IFERROR(VLOOKUP(Table7[[#This Row],[Cust_ID]],CustomersData[#All],2,0),"") -> Raghav | G15: N1009 | H15: =IFERROR(VLOOKUP(Table7[[#This Row],[HSN Code]],Table4[#All],2,0),"") -> Speaker | I15: 46023 | J15: =IFERROR(VLOOKUP(Table7[[#This Row],[HSN Code]],Table8[#All],6,0),"") -> -7 | K15: 3 | L15: =IFERROR(VLOOKUP(Table7[[#This Row],[HSN Code]],Table4[#All],4,0),"") -> 804 | M15: =IFERROR(Table7[[#This Row],[Units]]*Table7[[#This Row],[Price]],"") -> 2412
E16: 102 | F16: =IFERROR(VLOOKUP(Table7[[#This Row],[Cust_ID]],CustomersData[#All],2,0),"") -> Atul Ltd. | G16: N1001 | H16: =IFERROR(VLOOKUP(Table7[[#This Row],[HSN Code]],Table4[#All],2,0),"") -> SmartWatch | I16: 46023 | J16: =IFERROR(VLOOKUP(Table7[[#This Row],[HSN Code]],Table8[#All],6,0),"") -> 5 | K16: 1 | L16: =IFERROR(VLOOKUP(Table7[[#This Row],[HSN Code]],Table4[#All],4,0),"") -> 1176 | M16: =IFERROR(Table7[[#This Row],[Units]]*Table7[[#This Row],[Price]],"") -> 1176
E17: 105 | F17: =IFERROR(VLOOKUP(Table7[[#This Row],[Cust_ID]],CustomersData[#All],2,0),"") -> Jain tel | G17: N1002 | H17: =IFERROR(VLOOKUP(Table7[[#This Row],[HSN Code]],Table4[#All],2,0),"") -> Laptop HP i5 | I17: 46023 | J17: =IFERROR(VLOOKUP(Table7[[#This Row],[HSN Code]],Table8[#All],6,0),"") -> -2 | K17: 5 | L17: =IFERROR(VLOOKUP(Table7[[#This Row],[HSN Code]],Table4[#All],4,0),"") -> 41400 | M17: =IFERROR(Table7[[#This Row],[Units]]*Table7[[#This Row],[Price]],"") -> 207000
E18: 100 | F18: =IFERROR(VLOOKUP(Table7[[#This Row],[Cust_ID]],CustomersData[#All],2,0),"") -> Harsh | G18: N1003 | H18: =IFERROR(VLOOKUP(Table7[[#This Row],[HSN Code]],Table4[#All],2,0),"") -> Printer | I18: 46023 | J18: =IFERROR(VLOOKUP(Table7[[#This Row],[HSN Code]],Table8[#All],6,0),"") -> -3 | K18: 6 | L18: =IFERROR(VLOOKUP(Table7[[#This Row],[HSN Code]],Table4[#All],4,0),"") -> 5520 | M18: =IFERROR(Table7[[#This Row],[Units]]*Table7[[#This Row],[Price]],"") -> 33120

Sheet Inventory
E5: HSN Code | F5: Product Name | G5: Cost | H5: P Units | I5: S Units | J5: Stock | K5: Stock Amt | L5: Notification
E6: =Product!E8 -> N1001 | F6: =Product!F8 -> SmartWatch | G6: =Product!G8 -> 980 | H6: =SUMIF(PurchaseData[Product Name],Table8[[#This Row],[Product Name]],PurchaseData[Units]) -> 6 | I6: =SUMIF(Table7[Product Name],Table8[[#This Row],[Product Name]],Table7[Units]) -> 1 | J6: =Table8[[#This Row],[P Units]]-Table8[[#This Row],[S Units]] -> 5 | K6: =IFERROR(Table8[[#This Row],[Cost]]*Table8[[#This Row],[Stock]],"") -> 4900 | L6: =IFERROR(IF(J5<5,"📞 "&Table8[[#This Row],[Product Name]]&" Needs to re-order ! PH "&VLOOKUP(Table8[[#This Row],[HSN Code]],Table46[#All],4,0),""),"")
E7: =Product!E9 -> N1002 | F7: =Product!F9 -> Laptop HP i5 | G7: =Product!G9 -> 34500 | H7: =SUMIF(PurchaseData[Product Name],Table8[[#This Row],[Product Name]],PurchaseData[Units]) -> 3 | I7: =SUMIF(Table7[Product Name],Table8[[#This Row],[Product Name]],Table7[Units]) -> 5 | J7: =Table8[[#This Row],[P Units]]-Table8[[#This Row],[S Units]] -> -2 | K7: =IFERROR(Table8[[#This Row],[Cost]]*Table8[[#This Row],[Stock]],"") -> -69000 | L7: =IFERROR(IF(J6<5,"📞 "&Table8[[#This Row],[Product Name]]&" Needs to re-order ! PH "&VLOOKUP(Table8[[#This Row],[HSN Code]],Table46[#All],4,0),""),"")
E8: =Product!E10 -> N1003 | F8: =Product!F10 -> Printer | G8: =Product!G10 -> 4600 | H8: =SUMIF(PurchaseData[Product Name],Table8[[#This Row],[Product Name]],PurchaseData[Units]) -> 3 | I8: =SUMIF(Table7[Product Name],Table8[[#This Row],[Product Name]],Table7[Units]) -> 6 | J8: =Table8[[#This Row],[P Units]]-Table8[[#This Row],[S Units]] -> -3 | K8: =Table8[[#This Row],[Cost]]*Table8[[#This Row],[Stock]] -> -13800 | L8: =IFERROR(IF(J7<5,"📞 "&Table8[[#This Row],[Product Name]]&" Needs to re-order ! PH "&VLOOKUP(Table8[[#This Row],[HSN Code]],Table46[#All],4,0),""),"") -> 📞 Printer Needs to re-order ! PH 9874561231
E9: =Product!E11 -> N1004 | F9: =Product!F11 -> Desktop | G9: =Product!G11 -> 21000 | H9: =SUMIF(PurchaseData[Product Name],Table8[[#This Row],[Product Name]],PurchaseData[Units]) -> 16 | I9: =SUMIF(Table7[Product Name],Table8[[#This Row],[Product Name]],Table7[Units]) -> 4 | J9: =Table8[[#This Row],[P Units]]-Table8[[#This Row],[S Units]] -> 12 | K9: =Table8[[#This Row],[Cost]]*Table8[[#This Row],[Stock]] -> 252000 | L9: =IFERROR(IF(J8<5,"📞 "&Table8[[#This Row],[Product Name]]&" Needs to re-order ! PH "&VLOOKUP(Table8[[#This Row],[HSN Code]],Table46[#All],4,0),""),"") -> 📞 Desktop Needs to re-order ! PH 9874561231
E10: =Product!E12 -> N1005 | F10: =Product!F12 -> Mouse | G10: =Product!G12 -> 200 | H10: =SUMIF(PurchaseData[Product Name],Table8[[#This Row],[Product Name]],PurchaseData[Units]) -> 6 | I10: =SUMIF(Table7[Product Name],Table8[[#This Row],[Product Name]],Table7[Units]) -> 6 | J10: =Table8[[#This Row],[P Units]]-Table8[[#This Row],[S Units]] -> 0 | K10: =Table8[[#This Row],[Cost]]*Table8[[#This Row],[Stock]] -> 0 | L10: =IFERROR(IF(J9<5,"📞 "&Table8[[#This Row],[Product Name]]&" Needs to re-order ! PH "&VLOOKUP(Table8[[#This Row],[HSN Code]],Table46[#All],4,0),""),"")
E11: =Product!E13 -> N1006 | F11: =Product!F13 -> Keyboard | G11: =Product!G13 -> 340 | H11: =SUMIF(PurchaseData[Product Name],Table8[[#This Row],[Product Name]],PurchaseData[Units]) -> 0 | I11: =SUMIF(Table7[Product Name],Table8[[#This Row],[Product Name]],Table7[Units]) -> 2 | J11: =Table8[[#This Row],[P Units]]-Table8[[#This Row],[S Units]] -> -2 | K11: =Table8[[#This Row],[Cost]]*Table8[[#This Row],[Stock]] -> -680 | L11: =IFERROR(IF(J10<5,"📞 "&Table8[[#This Row],[Product Name]]&" Needs to re-order ! PH "&VLOOKUP(Table8[[#This Row],[HSN Code]],Table46[#All],4,0),""),"") -> 📞 Keyboard Needs to re-order ! PH 9874561231
E12: =Product!E14 -> N1007 | F12: =Product!F14 -> Camera | G12: =Product!G14 -> 52000 | H12: =SUMIF(PurchaseData[Product Name],Table8[[#This Row],[Product Name]],PurchaseData[Units]) -> 0 | I12: =SUMIF(Table7[Product Name],Table8[[#This Row],[Product Name]],Table7[Units]) -> 5 | J12: =Table8[[#This Row],[P Units]]-Table8[[#This Row],[S Units]] -> -5 | K12: =Table8[[#This Row],[Cost]]*Table8[[#This Row],[Stock]] -> -260000 | L12: =IFERROR(IF(J11<5,"📞 "&Table8[[#This Row],[Product Name]]&" Needs to re-order ! PH "&VLOOKUP(Table8[[#This Row],[HSN Code]],Table46[#All],4,0),""),"") -> 📞 Camera Needs to re-order ! PH 9874561231
E13: =Product!E15 -> N1008 | F13: =Product!F15 -> Headphone | G13: =Product!G15 -> 799 | H13: =SUMIF(PurchaseData[Product Name],Table8[[#This Row],[Product Name]],PurchaseData[Units]) -> 7 | I13: =SUMIF(Table7[Product Name],Table8[[#This Row],[Product Name]],Table7[Units]) -> 2 | J13: =Table8[[#This Row],[P Units]]-Table8[[#This Row],[S Units]] -> 5 | K13: =Table8[[#This Row],[Cost]]*Table8[[#This Row],[Stock]] -> 3995 | L13: =IFERROR(IF(J12<5,"📞 "&Table8[[#This Row],[Product Name]]&" Needs to re-order ! PH "&VLOOKUP(Table8[[#This Row],[HSN Code]],Table46[#All],4,0),""),"") -> 📞 Headphone Needs to re-order ! PH 9874561231
E14: =Product!E16 -> N1009 | F14: =Product!F16 -> Speaker | G14: =Product!G16 -> 870 | H14: =SUMIF(PurchaseData[Product Name],Table8[[#This Row],[Product Name]],PurchaseData[Units]) -> 2 | I14: =SUMIF(Table7[Product Name],Table8[[#This Row],[Product Name]],Table7[Units]) -> 9 | J14: =Table8[[#This Row],[P Units]]-Table8[[#This Row],[S Units]] -> -7 | K14: =Table8[[#This Row],[Cost]]*Table8[[#This Row],[Stock]] -> -6090 | L14: =IFERROR(IF(J13<5,"📞 "&Table8[[#This Row],[Product Name]]&" Needs to re-order ! PH "&VLOOKUP(Table8[[#This Row],[HSN Code]],Table46[#All],4,0),""),"")
E15: =Product!E17 -> N1010 | F15: =Product!F17 -> Tablets | G15: =Product!G17 -> 23500 | H15: =SUMIF(PurchaseData[Product Name],Table8[[#This Row],[Product Name]],PurchaseData[Units]) -> 0 | I15: =SUMIF(Table7[Product Name],Table8[[#This Row],[Product Name]],Table7[Units]) -> 0 | J15: =Table8[[#This Row],[P Units]]-Table8[[#This Row],[S Units]] -> 0 | K15: =Table8[[#This Row],[Cost]]*Table8[[#This Row],[Stock]] -> 0 | L15: =IFERROR(IF(J14<5,"📞 "&Table8[[#This Row],[Product Name]]&" Needs to re-order ! PH "&VLOOKUP(Table8[[#This Row],[HSN Code]],Table46[#All],4,0),""),"") -> 📞 Tablets Needs to re-order ! PH 9874561231

Sheet Pivot
A2: Count of Name | C2: Customers | F2: Row Labels | G2: Sum of S Units
A3: 7 | C3: =GETPIVOTDATA("Name",$A$2) -> 7 | F3: Speaker | G3: 9
F4: Printer | G4: 6
A5: Count of Product Name | C5: Products | F5: Mouse | G5: 6
A6: 10 | C6: =GETPIVOTDATA("Product Name",$A$5) -> 10 | F6: Laptop HP i5 | G6: 5
F7: Camera | G7: 5
A8: Sum of Amount | C8: Purchase Amt | F8: Grand Total | G8: 31
A9: 467713 | C9: =GETPIVOTDATA("Amount",$A$8) -> 467713
A11: Sum of Discount | C11: Sale Amt | F11: Row Labels | G11: Sum of Discount
A12: 665504 | C12: =GETPIVOTDATA("Discount",$A$11) -> 665504 | F12: Relaince | G12: 312000
F13: Jain tel | G13: 207000
A14: Sum of Stock Amt | C14: Stock Amt | F14: Raghav | G14: 103212
A15: -88675 | C15: =GETPIVOTDATA("Stock Amt",$A$14) -> -88675 | F15: Harsh | G15: 35036
F16: Ram Sales | G16: 4824
C17: Profit/loss | F17: Grand Total | G17: 662072
C18: =C15+C12-C9 -> 109116
A20: Row Labels | B20: Sum of Stock
A21: Camera | B21: -5
A22: Desktop | B22: 12
A23: Headphone | B23: 5
A24: Keyboard | B24: -2
A25: Laptop HP i5 | B25: -2
A26: Mouse | B26: 0
A27: Printer | B27: -3
A28: SmartWatch | B28: 5
A29: Speaker | B29: -7
A30: Tablets | B30: 0
A31: Grand Total | B31: 3
